Metadata-Version: 2.4
Name: adafruit-circuitpython-bmp5xx
Version: 1.1.1
Summary: CircuitPython library for the BMP580 / BMP581 / BMP585 / etc barometric pressure sensors.
Author-email: Adafruit Industries <circuitpython@adafruit.com>
License: MIT
Project-URL: Homepage, https://github.com/adafruit/Adafruit_CircuitPython_BMP5xx
Keywords: adafruit,blinka,circuitpython,micropython,bmp5xx,temperature,sensor,pressure,BMP580,BMP581,BMP585,temp
Classifier: Intended Audience :: Developers
Classifier: Topic :: Software Development :: Libraries
Classifier: Topic :: Software Development :: Embedded Systems
Classifier: Topic :: System :: Hardware
Classifier: License :: OSI Approved :: MIT License
Classifier: Programming Language :: Python :: 3
License-File: LICENSE
Requires-Dist: Adafruit-Blinka
Requires-Dist: adafruit-circuitpython-busdevice
Requires-Dist: adafruit-circuitpython-register
Provides-Extra: optional
Dynamic: license-file
